MISP_maltego/__init__.py
MISP_maltego/resources/__init__.py
MISP_maltego/resources/etc/MISP_maltego.conf
MISP_maltego/resources/etc/__init__.py
MISP_maltego/resources/external/__init__.py
MISP_maltego/resources/images/__init__.py
MISP_maltego/resources/maltego/__init__.py
MISP_maltego/resources/maltego/entities.mtz
MISP_maltego/resources/maltego/misp_MISPEventToAll.machine
MISP_maltego/resources/maltego/misp_MISPEventToAttributes.machine
MISP_maltego/transforms/__init__.py
MISP_maltego/transforms/attributetoevent.py
MISP_maltego/transforms/eventtoattributes.py
MISP_maltego/transforms/galaxytoevent.py
MISP_maltego/transforms/common/__init__.py
MISP_maltego/transforms/common/entities.py
MISP_maltego/transforms/common/mappings.py
MISP_maltego/transforms/common/util.py
MISP_maltego-1.4.7.dist-info/LICENSE
MISP_maltego-1.4.7.dist-info/METADATA
MISP_maltego-1.4.7.dist-info/WHEEL
MISP_maltego-1.4.7.dist-info/top_level.txt
MISP_maltego-1.4.7.dist-info/RECORD
