Metadata-Version: 2.1
Name: MISP-maltego
Version: 1.4.7
Summary: Maltego transform for interacting with a MISP Threat Sharing community and with MITRE ATT&CK.
Home-page: https://github.com/MISP/MISP-maltego
Author: Christophe Vandeplas
Author-email: christophe@vandeplas.com
Maintainer: Christophe Vandeplas
License: AGPLv3
Platform: UNKNOWN
Classifier: License :: OSI Approved :: GNU Affero General Public License v3
Classifier: Development Status :: 4 - Beta
Classifier: Operating System :: POSIX :: Linux
Classifier: Intended Audience :: Science/Research
Classifier: Intended Audience :: Telecommunications Industry
Classifier: Intended Audience :: Information Technology
Classifier: Programming Language :: Python :: 3
Classifier: Topic :: Security
Classifier: Topic :: Internet
Requires-Python: >=3.5
Requires-Dist: canari (<4,>=3.3.10)
Requires-Dist: PyMISP (>=2.4.127)
